numberlink/__init__.py
numberlink/__main__.py
numberlink/cli.py
numberlink/config.py
numberlink/env.py
numberlink/generator.py
numberlink/level_setup.py
numberlink/levels.py
numberlink/main.py
numberlink/notebook_viewer.py
numberlink/number_render.py
numberlink/py.typed
numberlink/registration.py
numberlink/render_utils.py
numberlink/types.py
numberlink/vector_env.py
numberlink/viewer.py
numberlink/assets/numberlink-logo.png
numberlink/assets/levels/5x5_ha_4c_016.sol.json
numberlink/assets/levels/5x5_ha_4c_016.txt
numberlink/assets/levels/5x5_ha_4c_026.sol.json
numberlink/assets/levels/5x5_ha_4c_026.txt
numberlink/assets/levels/5x5_ra_4c_011.sol.json
numberlink/assets/levels/5x5_ra_4c_011.txt
numberlink/assets/levels/5x5_ra_4c_021.sol.json
numberlink/assets/levels/5x5_ra_4c_021.txt
numberlink/assets/levels/6x6_ha_5c_012.sol.json
numberlink/assets/levels/6x6_ha_5c_012.txt
numberlink/assets/levels/6x6_ha_5c_022.sol.json
numberlink/assets/levels/6x6_ha_5c_022.txt
numberlink/assets/levels/6x6_ra_5c_017.sol.json
numberlink/assets/levels/6x6_ra_5c_017.txt
numberlink/assets/levels/6x6_ra_5c_027.sol.json
numberlink/assets/levels/6x6_ra_5c_027.txt
numberlink/assets/levels/7x7_ha_6c_018.sol.json
numberlink/assets/levels/7x7_ha_6c_018.txt
numberlink/assets/levels/7x7_ha_6c_028.sol.json
numberlink/assets/levels/7x7_ha_6c_028.txt
numberlink/assets/levels/7x7_ra_6c_013.sol.json
numberlink/assets/levels/7x7_ra_6c_013.txt
numberlink/assets/levels/7x7_ra_6c_023.sol.json
numberlink/assets/levels/7x7_ra_6c_023.txt
numberlink/assets/levels/8x8_ha_6c_014.sol.json
numberlink/assets/levels/8x8_ha_6c_014.txt
numberlink/assets/levels/8x8_ha_6c_024.sol.json
numberlink/assets/levels/8x8_ha_6c_024.txt
numberlink/assets/levels/8x8_ra_6c_019.sol.json
numberlink/assets/levels/8x8_ra_6c_019.txt
numberlink/assets/levels/8x8_ra_6c_029.sol.json
numberlink/assets/levels/8x8_ra_6c_029.txt
numberlink/assets/levels/9x9_ha_7c_020.sol.json
numberlink/assets/levels/9x9_ha_7c_020.txt
numberlink-0.1.5.dist-info/METADATA
numberlink-0.1.5.dist-info/WHEEL
numberlink-0.1.5.dist-info/entry_points.txt
numberlink-0.1.5.dist-info/licenses/LICENSE
numberlink-0.1.5.dist-info/RECORD
