Metadata-Version: 2.4
Name: numberlink
Version: 0.1.5
Summary: NumberLink puzzle environment for Gymnasium
Project-URL: GitHub, https://github.com/misaghsoltani/NumberLink/
Project-URL: Documentation, https://misaghsoltani.github.io/NumberLink/
Author-email: Misagh Soltani <misaghsoltani@gmail.com>
License-Expression: MIT
License-File: LICENSE
Keywords: AI,Game,Gymnasium,NumberLink,OpenAI Gym,Puzzle,deep reinforcement learning,gym,heuristic search,pathfinding,planning,reinforcement learning,search
Classifier: Intended Audience :: Science/Research
Classifier: License :: OSI Approved :: MIT License
Classifier: Operating System :: OS Independent
Classifier: Programming Language :: Python :: 3
Classifier: Programming Language :: Python :: 3.10
Classifier: Programming Language :: Python :: 3.11
Classifier: Programming Language :: Python :: 3.12
Classifier: Programming Language :: Python :: 3.13
Classifier: Programming Language :: Python :: 3.14
Classifier: Topic :: Scientific/Engineering :: Artificial Intelligence
Classifier: Typing :: Typed
Requires-Python: >=3.10
Requires-Dist: gymnasium<2,>=1.0
Requires-Dist: numpy<3,>=2.0
Requires-Dist: pygame<3,>=2.0
Provides-Extra: notebook
Requires-Dist: ipyevents<3,>=2.0.4; extra == 'notebook'
Requires-Dist: ipython<10,>=9.6.0; extra == 'notebook'
Requires-Dist: ipywidgets<9,>=8.1.7; extra == 'notebook'
Requires-Dist: pillow<13,>=12.0.0; extra == 'notebook'
